pptestopawell/__init__.py
pptestopawell/m_mod_pptest.py
pptestopawell-0.0.1.dist-info/LICENCE.txt
pptestopawell-0.0.1.dist-info/METADATA
pptestopawell-0.0.1.dist-info/WHEEL
pptestopawell-0.0.1.dist-info/top_level.txt
pptestopawell-0.0.1.dist-info/RECORD
