Metadata-Version: 2.1
Name: pptestopawell
Version: 0.0.1
Summary: pptest
Author-email: AZ <email@gmail.com>
License: MIT License
Keywords: pptestopawell,personal data
Classifier: Framework :: IDLE
Classifier: License :: Free For Educational Use
Requires-Python: >=3.0
License-File: LICENCE.txt
Requires-Dist: numpy ; python_version >= "3.0"
